brainfuck.py
python_brainfuck-0.9.1.dist-info/LICENSE
python_brainfuck-0.9.1.dist-info/METADATA
python_brainfuck-0.9.1.dist-info/WHEEL
python_brainfuck-0.9.1.dist-info/top_level.txt
python_brainfuck-0.9.1.dist-info/RECORD
