Metadata-Version: 2.1
Name: python-brainfuck
Version: 0.9.1
Summary: Brainfuck to Python AST compilation and integration
Home-page: https://github.com/koirikivi/brainfuck
Author: Rainer Koirikivi
Author-email: rainer@koirikivi.fi
License: MIT
Keywords: python brainfuck ast compiler integration
Platform: UNKNOWN
Classifier: Intended Audience :: Developers
Classifier: Topic :: Software Development :: Compilers
Classifier: License :: OSI Approved :: MIT License
Classifier: Programming Language :: Python :: 2
Classifier: Programming Language :: Python :: 2.7
Classifier: Programming Language :: Python :: 3
Classifier: Programming Language :: Python :: 3.4
Classifier: Programming Language :: Python :: 3.5
Classifier: Programming Language :: Python :: 3.6
Classifier: Programming Language :: Python :: 3.7
Classifier: Programming Language :: Python :: Implementation :: CPython
Classifier: Programming Language :: Python :: Implementation :: PyPy
